expectation_reflection/__init__.py
expectation_reflection/classification.py
expectation_reflection/classification_no_self.py
expectation_reflection/classification_v1.py
expectation_reflection/function.py
expectation_reflection/utils.py
expectation_reflection-0.0.10.dist-info/LICENSE
expectation_reflection-0.0.10.dist-info/METADATA
expectation_reflection-0.0.10.dist-info/WHEEL
expectation_reflection-0.0.10.dist-info/top_level.txt
expectation_reflection-0.0.10.dist-info/RECORD
