Metadata-Version: 2.1
Name: expectation-reflection
Version: 0.0.10
Summary: Expectation Reflection for classification
Home-page: https://github.com/danhtaihoang/expectation_reflection
Author: Danh-Tai HOANG
Author-email: hoangdanhtai@gmail.com
License: MIT
Keywords: machine learning,classification,network inference,statistics
Platform: UNKNOWN
Classifier: Programming Language :: Python :: 3
Classifier: License :: OSI Approved :: MIT License
Classifier: Operating System :: OS Independent
Requires-Python: >=3.6
